my_first_say_hello_package/__init__.py
my_first_say_hello_package/module.py
my_first_say_hello_package-0.1.0.dist-info/METADATA
my_first_say_hello_package-0.1.0.dist-info/WHEEL
my_first_say_hello_package-0.1.0.dist-info/top_level.txt
my_first_say_hello_package-0.1.0.dist-info/RECORD
